docbridge/__init__.py
docbridge-0.0.1.dist-info/METADATA
docbridge-0.0.1.dist-info/WHEEL
docbridge-0.0.1.dist-info/RECORD
