Metadata-Version: 2.1
Name: docbridge
Version: 0.0.1
Summary: A thin abstraction layer over BSON documents, to keep your data model agile.
Author-email: Mark Smith <mark.smith@mongodb.com>
Classifier: Development Status :: 1 - Planning
Classifier: Intended Audience :: Developers
Classifier: License :: OSI Approved :: Apache Software License
Classifier: Operating System :: OS Independent
Classifier: Programming Language :: Python :: 3
Classifier: Topic :: Database
Requires-Python: >=3.7
Requires-Dist: pymongo[srv]~=4.6.0
